{"cameraMode":{"drawMode":0,"name":"Shaded","section":"Shading Mode"},"sceneLighting":false,"audioPlay":false,"sceneViewState":{"m_AlwaysRefresh":false,"showFog":true,"showSkybox":false,"showFlares":true,"showImageEffects":true,"showParticleSystems":true,"showVisualEffectGraphs":true,"m_FxEnabled":true},"in2DMode":false,"pivot":{"x":0.0,"y":0.0,"z":0.9474999904632568},"rotation":{"x":0.12820814549922944,"y":0.838694155216217,"z":-0.4794359803199768,"w":0.2242797315120697},"size":1.6109799146652222,"orthographic":false}